aviary/__init__.py
aviary/cgcnn/__init__.py
aviary/cgcnn/data.py
aviary/cgcnn/model.py
aviary/core.py
aviary/data.py
aviary/embeddings/element/README.md
aviary/embeddings/element/cgcnn92.json
aviary/embeddings/element/matscholar200.json
aviary/embeddings/element/megnet16.json
aviary/embeddings/element/onehot112.json
aviary/embeddings/wyckoff/README.md
aviary/embeddings/wyckoff/bra-alg-off.json
aviary/losses.py
aviary/networks.py
aviary/predict.py
aviary/roost/__init__.py
aviary/roost/data.py
aviary/roost/model.py
aviary/scatter.py
aviary/segments.py
aviary/utils.py
aviary/wren/__init__.py
aviary/wren/data.py
aviary/wren/model.py
aviary/wren/utils.py
aviary/wrenformer/__init__.py
aviary/wrenformer/data.py
aviary/wrenformer/model.py
aviary_models-1.2.1.dist-info/WHEEL
aviary_models-1.2.1.dist-info/METADATA
aviary_models-1.2.1.dist-info/RECORD
