Metadata-Version: 2.3
Name: aviary-models
Version: 1.2.1
Summary: A collection of machine learning models for materials discovery
Keywords: Graph Neural Network,Machine Learning,Materials Discovery,Materials Informatics,Materials Science,Roost,Self-Attention,Transformer,Wren,Wyckoff positions
Author: Rhys Goodall
Author-email: Rhys Goodall <rhys.goodall@outlook.com>
License: MIT License
Classifier: Intended Audience :: Science/Research
Classifier: License :: OSI Approved :: MIT License
Classifier: Operating System :: OS Independent
Classifier: Programming Language :: Python :: 3.10
Classifier: Programming Language :: Python :: 3.11
Classifier: Topic :: Scientific/Engineering :: Artificial Intelligence
Classifier: Topic :: Scientific/Engineering :: Chemistry
Classifier: Topic :: Scientific/Engineering :: Physics
Requires-Dist: numpy>=2,<3
Requires-Dist: pandas
Requires-Dist: pymatgen>=2025.4.10
Requires-Dist: scikit-learn
Requires-Dist: tensorboard
Requires-Dist: torch>=2.3.0
Requires-Dist: tqdm
Requires-Dist: typing-extensions
Requires-Dist: wandb
Requires-Dist: moyopy>=0.3.3 ; extra == 'moyopy'
Requires-Dist: matminer ; extra == 'test'
Requires-Dist: moyopy>=0.3.3 ; extra == 'test'
Requires-Dist: pytest ; extra == 'test'
Requires-Dist: pytest-cov ; extra == 'test'
Requires-Python: >=3.10
Project-URL: Repo, https://github.com/CompRhys/aviary
Provides-Extra: moyopy
Provides-Extra: test
